pyforc/__init__.py
pyforc/core/README.md
pyforc/core/__init__.py
pyforc/core/config.py
pyforc/core/coordinates.py
pyforc/core/forc.py
pyforc/core/forcdata.py
pyforc/core/ingester.py
pyforc/core/ops.py
pyforc/core/plot.py
pyforc-1.2.0.dist-info/LICENSE
pyforc-1.2.0.dist-info/METADATA
pyforc-1.2.0.dist-info/WHEEL
pyforc-1.2.0.dist-info/top_level.txt
pyforc-1.2.0.dist-info/RECORD
