Metadata-Version: 2.1
Name: pyforc
Version: 1.2.0
Summary: FORC analysis in Python
Author: Peyton Murray
License: Copyright (c) 2024 Peyton Murray
Project-URL: Homepage, https://github.com/peytondmurray/pyforc
Classifier: Programming Language :: Python :: 3
Classifier: License :: OSI Approved :: BSD License
Classifier: Operating System :: OS Independent
Requires-Python: >=3.11
License-File: LICENSE
Requires-Dist: numpy
Requires-Dist: scipy
Requires-Dist: matplotlib
Provides-Extra: dev
Requires-Dist: pre-commit >=3.6.0 ; extra == 'dev'
Provides-Extra: doc
Requires-Dist: sphinx ; extra == 'doc'
Requires-Dist: myst-parser ; extra == 'doc'
Provides-Extra: test
Requires-Dist: pytest ; extra == 'test'
